[{
  "_id": {
    "$oid": "67079aa30067b0b322dc149c"
  },
  "NOMOR_SPK": "TESTING/IMPORT2",
  "ID_MUTASI_MASUK": "6a9d3601-e250-4435-94e0-3592783e46b0",
  "ID_SATKER": "a3c0eca8-04c4-49a4-9ee6-647312642778",
  "ID_INSTANSI": "32e2b2b3-907f-a499-9bda-bc549c992564",
  "KODE_BARANG": "1.01.03.06.002.000008",
  "NAMA_BARANG": "Lampu Halogen 6 V 20 W",
  "KATEGORI": 52,
  "HARGA": 4032600,
  "TANGGAL": "2023-05-12 00:00:00",
  "QTY": 2,
  "STOCK_AWAL": 11,
  "STOCK_AKHIR": 13,
  "ID_PENGGUNA": "929a7068-2d5d-45e0-916e-30645965aefb",
  "KETERANGAN": "-",
  "STATUS": "ditunda"
},
{
  "_id": {
    "$oid": "67079aa30067b0b322dc149f"
  },
  "NOMOR_SPK": "TESTING/IMPORT2",
  "ID_MUTASI_MASUK": "a169f58b-ec15-4fc9-8695-eca5e17473d3",
  "ID_SATKER": "a3c0eca8-04c4-49a4-9ee6-647312642778",
  "ID_INSTANSI": "32e2b2b3-907f-a499-9bda-bc549c992564",
  "KODE_BARANG": "1.01.03.01.001.000004",
  "NAMA_BARANG": "Spidol Kecil",
  "KATEGORI": 52,
  "HARGA": 11100,
  "TANGGAL": "2023-05-12 00:00:00",
  "QTY": 2,
  "STOCK_AWAL": 10,
  "STOCK_AKHIR": 12,
  "ID_PENGGUNA": "929a7068-2d5d-45e0-916e-30645965aefb",
  "KETERANGAN": "-",
  "STATUS": "ditunda"
},
{
  "_id": {
    "$oid": "67079b2d0067b0b322dc14bf"
  },
  "NOMOR_SPK": "12345678",
  "ID_MUTASI_MASUK": "5e90f021-987f-42f7-85f6-7e1572e570ca",
  "ID_SATKER": "929a7068-2d5d-45e0-916e-30645965aefb",
  "ID_INSTANSI": "32e2b2b3-907f-a499-9bda-bc549c992564",
  "KODE_BARANG": "1.01.03.06.002.000008",
  "NAMA_BARANG": "Lampu Halogen 6 V 20 W",
  "KATEGORI": 52,
  "HARGA": 4032600,
  "TANGGAL": "2024-10-10 16:13:47",
  "QTY": 2,
  "STOCK_AWAL": 13,
  "STOCK_AKHIR": 15,
  "ID_PENGGUNA": "929a7068-2d5d-45e0-916e-30645965aefb",
  "KETERANGAN": "-",
  "STATUS": "ditunda"
},
{
  "_id": {
    "$oid": "67079b2d0067b0b322dc14c2"
  },
  "NOMOR_SPK": "12345678",
  "ID_MUTASI_MASUK": "4965d991-7285-4806-81ae-2c8f958b9e94",
  "ID_SATKER": "929a7068-2d5d-45e0-916e-30645965aefb",
  "ID_INSTANSI": "32e2b2b3-907f-a499-9bda-bc549c992564",
  "KODE_BARANG": "1.01.03.01.001.000004",
  "NAMA_BARANG": "Spidol Kecil",
  "KATEGORI": 52,
  "HARGA": 11100,
  "TANGGAL": "2024-10-10 16:13:47",
  "QTY": 2,
  "STOCK_AWAL": 12,
  "STOCK_AKHIR": 14,
  "ID_PENGGUNA": "929a7068-2d5d-45e0-916e-30645965aefb",
  "KETERANGAN": "-",
  "STATUS": "ditunda"
},
{
  "_id": {
    "$oid": "6707a0b40067b0b322dc1532"
  },
  "NOMOR_SPK": "B002311",
  "ID_MUTASI_MASUK": "e6435da4-3031-4591-8a59-aab68a65bf99",
  "ID_SATKER": "929a7068-2d5d-45e0-916e-30645965aefb",
  "ID_INSTANSI": "32e2b2b3-907f-a499-9bda-bc549c992564",
  "KODE_BARANG": "1.01.03.06.002.000008",
  "NAMA_BARANG": "Lampu Halogen 6 V 20 W",
  "KATEGORI": 52,
  "HARGA": 4032600,
  "TANGGAL": "2024-10-10 16:38:47",
  "QTY": 5,
  "STOCK_AWAL": 15,
  "STOCK_AKHIR": 20,
  "ID_PENGGUNA": "929a7068-2d5d-45e0-916e-30645965aefb",
  "KETERANGAN": "-",
  "STATUS": "ditunda"
},
{
  "_id": {
    "$oid": "6707a0b40067b0b322dc1535"
  },
  "NOMOR_SPK": "B002311",
  "ID_MUTASI_MASUK": "f0ef3ad2-d31d-42b8-a4f5-4e3922c7f408",
  "ID_SATKER": "929a7068-2d5d-45e0-916e-30645965aefb",
  "ID_INSTANSI": "32e2b2b3-907f-a499-9bda-bc549c992564",
  "KODE_BARANG": "1.01.03.01.001.000004",
  "NAMA_BARANG": "Spidol Kecil",
  "KATEGORI": 52,
  "HARGA": 11100,
  "TANGGAL": "2024-10-10 16:38:47",
  "QTY": 2,
  "STOCK_AWAL": 14,
  "STOCK_AKHIR": 16,
  "ID_PENGGUNA": "929a7068-2d5d-45e0-916e-30645965aefb",
  "KETERANGAN": "-",
  "STATUS": "ditunda"
}]